net_templates/__init__.py
net_templates/definitions.py
net_templates/templar.py
net_templates/filters/NetFilters.py
net_templates/filters/__init__.py
net_templates/templates/ios/ios_aaa_accounting.j2
net_templates/templates/ios/ios_aaa_accounting_method.j2
net_templates/templates/ios/ios_aaa_action_list.j2
net_templates/templates/ios/ios_aaa_authentication.j2
net_templates/templates/ios/ios_aaa_authentication_method.j2
net_templates/templates/ios/ios_aaa_authorization.j2
net_templates/templates/ios/ios_aaa_authorization_method.j2
net_templates/templates/ios/ios_aaa_config.j2
net_templates/templates/ios/ios_aaa_group_radius.j2
net_templates/templates/ios/ios_aaa_group_tacacs.j2
net_templates/templates/ios/ios_aaa_radius_all.j2
net_templates/templates/ios/ios_aaa_server_radius.j2
net_templates/templates/ios/ios_aaa_server_tacacs.j2
net_templates/templates/ios/ios_aaa_tacacs_all.j2
net_templates/templates/ios/ios_acl_all.j2
net_templates/templates/ios/ios_acl_extended.j2
net_templates/templates/ios/ios_acl_standard.j2
net_templates/templates/ios/ios_acl_standard_ipv4.j2
net_templates/templates/ios/ios_common_extra_config.j2
net_templates/templates/ios/ios_common_macros.j2
net_templates/templates/ios/ios_interface_base.j2
net_templates/templates/ios/ios_interface_bfd.j2
net_templates/templates/ios/ios_interface_discovery_cdp.j2
net_templates/templates/ios/ios_interface_discovery_lldp.j2
net_templates/templates/ios/ios_interface_hsrp.j2
net_templates/templates/ios/ios_interface_hsrp_group.j2
net_templates/templates/ios/ios_interface_ipv4.j2
net_templates/templates/ios/ios_interface_isis.j2
net_templates/templates/ios/ios_interface_l2_port.j2
net_templates/templates/ios/ios_interface_l3_port.j2
net_templates/templates/ios/ios_interface_lag_member.j2
net_templates/templates/ios/ios_interface_mode.j2
net_templates/templates/ios/ios_interface_ospf.j2
net_templates/templates/ios/ios_interface_service_instance.j2
net_templates-0.2.0.dist-info/LICENSE
net_templates-0.2.0.dist-info/METADATA
net_templates-0.2.0.dist-info/WHEEL
net_templates-0.2.0.dist-info/top_level.txt
net_templates-0.2.0.dist-info/RECORD
