Metadata-Version: 2.1
Name: net-templates
Version: 0.2.0
Summary: Network Config Templates
Home-page: UNKNOWN
Author: Miroslav Hudec <http://github.com/mihudec>
License: UNKNOWN
Platform: UNKNOWN
License-File: LICENSE
Requires-Dist: net-models (>=0.2.0)
Requires-Dist: pydantic
Requires-Dist: jinja2
Requires-Dist: pyyaml
Requires-Dist: typing-extensions
Requires-Dist: jmespath
